.coveragerc
AUTHORS
CHANGELOG.txt
DESCRIPTION
LICENSE
MANIFEST.in
Makefile
README.rst
manage.py
setup.cfg
setup.py
test_requirements.txt
companies/__init__.py
companies/__init__.pyc
companies/admin.py
companies/models.py
companies/migrations/0001_initial.py
companies/migrations/0002_auto_20150506_1251.py
companies/migrations/0003_auto_20150526_1255.py
companies/migrations/0004_companynamechange.py
companies/migrations/0005_remove_company_previous_name.py
companies/migrations/0006_auto_20150617_1432.py
companies/migrations/0007_company_trade_name.py
companies/migrations/0008_auto_20150622_1424.py
companies/migrations/0009_auto_20150626_1917.py
companies/migrations/0010_auto_20150626_1924.py
companies/migrations/0011_company_latest_incorporation_date.py
companies/migrations/0012_remove_company_is_listed.py
companies/migrations/0013_auto_20150923_1119.py
companies/migrations/0014_auto_20150924_1044.py
companies/migrations/__init__.py
companies/settings/__init__.py
companies/settings/sphinx_documentation.py
companies/settings/test_settings.py
companies/tests/__init__.py
companies/tests/models_tests.py
companies/tests/runtests.py
valuehorizon_companies.egg-info/PKG-INFO
valuehorizon_companies.egg-info/SOURCES.txt
valuehorizon_companies.egg-info/dependency_links.txt
valuehorizon_companies.egg-info/requires.txt
valuehorizon_companies.egg-info/top_level.txt