Metadata-Version: 1.0
Name: valuehorizon-companies
Version: 1.0
Summary: A Django-based Companies data toolkit. Part of the Valuehorizon application ecosystem.
